CHANGES.txt
LICENSE.txt
MANIFEST.in
README.txt
setup.py
src/p01/__init__.py
src/p01.locales.egg-info/PKG-INFO
src/p01.locales.egg-info/SOURCES.txt
src/p01.locales.egg-info/dependency_links.txt
src/p01.locales.egg-info/namespace_packages.txt
src/p01.locales.egg-info/not-zip-safe
src/p01.locales.egg-info/requires.txt
src/p01.locales.egg-info/top_level.txt
src/p01/locales/__init__.py
src/p01/locales/configure.zcml
src/p01/locales/extract.zcml
src/p01/locales/de-de/LC_MESSAGES/base.txt
src/p01/locales/de-de/LC_MESSAGES/p01.mo
src/p01/locales/de-de/LC_MESSAGES/p01.po
src/p01/locales/de/LC_MESSAGES/p01.mo
src/p01/locales/de/LC_MESSAGES/p01.po
src/p01/locales/en/LC_MESSAGES/p01.mo
src/p01/locales/en/LC_MESSAGES/p01.po
src/p01/locales/fr/LC_MESSAGES/p01.mo
src/p01/locales/fr/LC_MESSAGES/p01.po
src/p01/locales/it/LC_MESSAGES/p01.mo
src/p01/locales/it/LC_MESSAGES/p01.po