Metadata-Version: 1.0
Name: p01.locales
Version: 0.5.6
Summary: Translation for p01 package namespace
Home-page: http://pypi.python.org/pypi/p01.locales
Author: Roger Ineichen, Projekt01 GmbH
Author-email: dev@projekt01.ch
License: ZPL 2.1
Keywords: P01 i18n message factory Zope3
Platform: UNKNOWN
Classifier: Development Status :: 5 - Production/Stable
Classifier: Environment :: Web Environment
Classifier: Intended Audience :: Developers
Classifier: License :: OSI Approved :: Zope Public License
Classifier: Programming Language :: Python
Classifier: Natural Language :: English
Classifier: Operating System :: OS Independent
Classifier: Topic :: Internet :: WWW/HTTP
Classifier: Framework :: Zope3
